gnu6/__init__.py
gnu6/test.py
gnu6-0.1.dist-info/METADATA
gnu6-0.1.dist-info/WHEEL
gnu6-0.1.dist-info/top_level.txt
gnu6-0.1.dist-info/RECORD
