Metadata-Version: 2.1
Name: gnu6
Version: 0.1
Summary: GNU6
Home-page: https://github.com/gnuboard/gnu6
Download-URL: https://github.com/gnuboard/gnu6/archive/master.zip
Author: thisgun
Author-email: thisgun@sir.kr
Keywords: gnu6
Classifier: Programming Language :: Python :: 3
Classifier: Programming Language :: Python :: 3.2
Classifier: Programming Language :: Python :: 3.3
Classifier: Programming Language :: Python :: 3.4
Classifier: Programming Language :: Python :: 3.5
Classifier: Programming Language :: Python :: 3.6
Classifier: Programming Language :: Python :: 3.7
Requires-Python: >=3
